bestlab_platform/__init__.py
bestlab_platform/exceptions.py
bestlab_platform/hobo/__init__.py
bestlab_platform/hobo/webapi.py
bestlab_platform/tuya/LICENSE
bestlab_platform/tuya/__init__.py
bestlab_platform/tuya/device.py
bestlab_platform/tuya/openapi.py
bestlab_platform/tuya/openlogging.py
bestlab_platform-0.2.2.dist-info/LICENSE
bestlab_platform-0.2.2.dist-info/WHEEL
bestlab_platform-0.2.2.dist-info/METADATA
bestlab_platform-0.2.2.dist-info/RECORD
