Metadata-Version: 2.1
Name: bestlab_platform
Version: 0.2.2
Summary: Packages to access APIs for different platforms
Author-email: Wei Mu <wmu100@syr.edu>
Requires-Python: >=3.7
Classifier: License :: OSI Approved :: MIT License
Classifier: Topic :: Software Development :: Libraries :: Python Modules
Classifier: Operating System :: OS Independent
Classifier: Programming Language :: Python :: 3
Classifier: Programming Language :: Python :: 3.6
Classifier: Programming Language :: Python :: 3.7
Classifier: Programming Language :: Python :: 3.8
Classifier: Programming Language :: Python :: 3.9
Classifier: Programming Language :: Python :: 3.10
Requires-Dist: requests
Requires-Dist: sphinx ; extra == "docs"
Requires-Dist: sphinx-rtd-theme ; extra == "docs"
Requires-Dist: sphinx-autodoc-typehints ; extra == "docs"
Requires-Dist: flake8 ; extra == "linters"
Requires-Dist: flake8-bugbear ; extra == "linters"
Requires-Dist: flake8-comprehensions ; extra == "linters"
Requires-Dist: mypy ; extra == "linters"
Requires-Dist: types-requests ; extra == "linters"
Requires-Dist: python-dotenv ; extra == "utils"
Project-URL: Source, https://github.com/umonaca/bestlab_platform
Provides-Extra: docs
Provides-Extra: linters
Provides-Extra: utils
